Workbook

Sheet الملخص
A1: تقرير حالة بنود «DORR Chat + DORR AI — المرجع الموحد v5»
A2: الأساس: لون كل بند في ملف الورد (اتلوّن 2026-10-11، وفيه الشغل لحد 2026-10-13). اتحدث فوقه شغل الـ AI بتاع 2026-10-14 و2026-10-15 (شيت «اتغير بعد الملف»). الأرقام كلها معادلات على شيت «كل البنود»: لو غيّرت حالة بند هناك، الملخص بيتحدث لوحده.
A4: الجزء | B4: ✅ خلص | C4: 🟡 جزئي | D4: 🔵 لسه — ممكن يتعمل | E4: 🟠 مستني نظام تاني | F4: ⏸ مؤجل بقرار | G4: 🔴 مش هيتعمل | H4: الإجمالي | I4: نسبة الإنجاز
A5: مقدمة وقرارات عامة | B5: =COUNTIFS('كل البنود'!$B$2:$B$983,$A5,'كل البنود'!$H$2:$H$983,B$4) | C5: =COUNTIFS('كل البنود'!$B$2:$B$983,$A5,'كل البنود'!$H$2:$H$983,C$4) | D5: =COUNTIFS('كل البنود'!$B$2:$B$983,$A5,'كل البنود'!$H$2:$H$983,D$4) | E5: =COUNTIFS('كل البنود'!$B$2:$B$983,$A5,'كل البنود'!$H$2:$H$983,E$4) | F5: =COUNTIFS('كل البنود'!$B$2:$B$983,$A5,'كل البنود'!$H$2:$H$983,F$4) | G5: =COUNTIFS('كل البنود'!$B$2:$B$983,$A5,'كل البنود'!$H$2:$H$983,G$4) | H5: =SUM(B5:G5) | I5: =IFERROR((B5+C5/2)/(H5-F5-G5),0)
A6: الجزء الأول — نواة الدردشة والتكامل (1–97) | B6: =COUNTIFS('كل البنود'!$B$2:$B$983,$A6,'كل البنود'!$H$2:$H$983,B$4) | C6: =COUNTIFS('كل البنود'!$B$2:$B$983,$A6,'كل البنود'!$H$2:$H$983,C$4) | D6: =COUNTIFS('كل البنود'!$B$2:$B$983,$A6,'كل البنود'!$H$2:$H$983,D$4) | E6: =COUNTIFS('كل البنود'!$B$2:$B$983,$A6,'كل البنود'!$H$2:$H$983,E$4) | F6: =COUNTIFS('كل البنود'!$B$2:$B$983,$A6,'كل البنود'!$H$2:$H$983,F$4) | G6: =COUNTIFS('كل البنود'!$B$2:$B$983,$A6,'كل البنود'!$H$2:$H$983,G$4) | H6: =SUM(B6:G6) | I6: =IFERROR((B6+C6/2)/(H6-F6-G6),0)
A7: الجزء الثاني — توسعات الدردشة (98–207) | B7: =COUNTIFS('كل البنود'!$B$2:$B$983,$A7,'كل البنود'!$H$2:$H$983,B$4) | C7: =COUNTIFS('كل البنود'!$B$2:$B$983,$A7,'كل البنود'!$H$2:$H$983,C$4) | D7: =COUNTIFS('كل البنود'!$B$2:$B$983,$A7,'كل البنود'!$H$2:$H$983,D$4) | E7: =COUNTIFS('كل البنود'!$B$2:$B$983,$A7,'كل البنود'!$H$2:$H$983,E$4) | F7: =COUNTIFS('كل البنود'!$B$2:$B$983,$A7,'كل البنود'!$H$2:$H$983,F$4) | G7: =COUNTIFS('كل البنود'!$B$2:$B$983,$A7,'كل البنود'!$H$2:$H$983,G$4) | H7: =SUM(B7:G7) | I7: =IFERROR((B7+C7/2)/(H7-F7-G7),0)
A8: الجزء الثالث — DORR AI (367 بند) | B8: =COUNTIFS('كل البنود'!$B$2:$B$983,$A8,'كل البنود'!$H$2:$H$983,B$4) | C8: =COUNTIFS('كل البنود'!$B$2:$B$983,$A8,'كل البنود'!$H$2:$H$983,C$4) | D8: =COUNTIFS('كل البنود'!$B$2:$B$983,$A8,'كل البنود'!$H$2:$H$983,D$4) | E8: =COUNTIFS('كل البنود'!$B$2:$B$983,$A8,'كل البنود'!$H$2:$H$983,E$4) | F8: =COUNTIFS('كل البنود'!$B$2:$B$983,$A8,'كل البنود'!$H$2:$H$983,F$4) | G8: =COUNTIFS('كل البنود'!$B$2:$B$983,$A8,'كل البنود'!$H$2:$H$983,G$4) | H8: =SUM(B8:G8) | I8: =IFERROR((B8+C8/2)/(H8-F8-G8),0)
A9: ملحق Backlog (خارج النطاق الرسمي) | B9: =COUNTIFS('كل البنود'!$B$2:$B$983,$A9,'كل البنود'!$H$2:$H$983,B$4) | C9: =COUNTIFS('كل البنود'!$B$2:$B$983,$A9,'كل البنود'!$H$2:$H$983,C$4) | D9: =COUNTIFS('كل البنود'!$B$2:$B$983,$A9,'كل البنود'!$H$2:$H$983,D$4) | E9: =COUNTIFS('كل البنود'!$B$2:$B$983,$A9,'كل البنود'!$H$2:$H$983,E$4) | F9: =COUNTIFS('كل البنود'!$B$2:$B$983,$A9,'كل البنود'!$H$2:$H$983,F$4) | G9: =COUNTIFS('كل البنود'!$B$2:$B$983,$A9,'كل البنود'!$H$2:$H$983,G$4) | H9: =SUM(B9:G9) | I9: =IFERROR((B9+C9/2)/(H9-F9-G9),0)
A10: الإجمالي | B10: =SUM(B5:B9) | C10: =SUM(C5:C9) | D10: =SUM(D5:D9) | E10: =SUM(E5:E9) | F10: =SUM(F5:F9) | G10: =SUM(G5:G9) | H10: =SUM(H5:H9) | I10: =IFERROR((B10+C10/2)/(H10-F10-G10),0)
A12: حسب المسؤول
A13: يخص | B13: ✅ خلص | C13: 🟡 جزئي | D13: 🔵 لسه — ممكن يتعمل | E13: 🟠 مستني نظام تاني | F13: ⏸ مؤجل بقرار | G13: 🔴 مش هيتعمل | H13: الإجمالي | I13: نسبة الإنجاز
A14: الشات | B14: =COUNTIFS('كل البنود'!$J$2:$J$983,$A14,'كل البنود'!$H$2:$H$983,B$13) | C14: =COUNTIFS('كل البنود'!$J$2:$J$983,$A14,'كل البنود'!$H$2:$H$983,C$13) | D14: =COUNTIFS('كل البنود'!$J$2:$J$983,$A14,'كل البنود'!$H$2:$H$983,D$13) | E14: =COUNTIFS('كل البنود'!$J$2:$J$983,$A14,'كل البنود'!$H$2:$H$983,E$13) | F14: =COUNTIFS('كل البنود'!$J$2:$J$983,$A14,'كل البنود'!$H$2:$H$983,F$13) | G14: =COUNTIFS('كل البنود'!$J$2:$J$983,$A14,'كل البنود'!$H$2:$H$983,G$13) | H14: =SUM(B14:G14) | I14: =IFERROR((B14+C14/2)/(H14-F14-G14),0)
A15: دُرر AI | B15: =COUNTIFS('كل البنود'!$J$2:$J$983,$A15,'كل البنود'!$H$2:$H$983,B$13) | C15: =COUNTIFS('كل البنود'!$J$2:$J$983,$A15,'كل البنود'!$H$2:$H$983,C$13) | D15: =COUNTIFS('كل البنود'!$J$2:$J$983,$A15,'كل البنود'!$H$2:$H$983,D$13) | E15: =COUNTIFS('كل البنود'!$J$2:$J$983,$A15,'كل البنود'!$H$2:$H$983,E$13) | F15: =COUNTIFS('كل البنود'!$J$2:$J$983,$A15,'كل البنود'!$H$2:$H$983,F$13) | G15: =COUNTIFS('كل البنود'!$J$2:$J$983,$A15,'كل البنود'!$H$2:$H$983,G$13) | H15: =SUM(B15:G15) | I15: =IFERROR((B15+C15/2)/(H15-F15-G15),0)
A16: الإجمالي | B16: =SUM(B14:B15) | C16: =SUM(C14:C15) | D16: =SUM(D14:D15) | E16: =SUM(E14:E15) | F16: =SUM(F14:F15) | G16: =SUM(G14:G15) | H16: =SUM(H14:H15) | I16: =IFERROR((B16+C16/2)/(H16-F16-G16),0)
A18: نسبة الإنجاز = (خلص + نص الجزئي) ÷ (الإجمالي − المؤجل بقرار − اللي مش هيتعمل).
A19: «🟠 مستني نظام تاني» = البند محتاج نظام مركزي لسه ماتعملش: محرك الطلبات والخدمات، أو سير العمل، أو السلوك والثقة، أو مزود خرايط، أو المحفظة. الملاحظة جنب كل بند بتقول أنهي نظام.
A20: الـ Backlog (146 ميزة واتساب و78 من التطبيقات المنافسة) مكتوب في الملف للمعلومية بس، ومش متطلب تنفيذ.
A21: تعديلات بعد الملف: شغل دُرر AI بتاع 2026-10-14 (الذاكرة، والسياق المنقول، والبحث بالمعنى، والمشاريع، ومعرض المخرجات، وقواعد المصادر وفحصها، والـ Feature Flag بالدولة) و2026-10-15 (الصور في الشات، وربط أدوات الـ AI بباقات دُرر AI — ADR-013).

Sheet كل البنود
A1: # | B1: الجزء | C1: القسم | D1: رقم البند | E1: البند | F1: الوصف | G1: الحالة في ملف الورد (2026-10-11) | H1: الحالة الحالية | I1: آخر تحديث | J1: يخص | K1: ملاحظات
A2: 1 | B2: مقدمة وقرارات عامة | C2: قرار المنتج والتنفيذ | E2: هذه الوثيقة تجمع محتوى الملفات الثلاثة في مرجع واحد منظم، مع الحفاظ على الفصل المعماري بين Chat Core وطبقات التكامل وDORR AI. | G2: أخضر — خلص | H2: ✅ خلص | I2: 2026-10-11 | J2: الشات
A3: 2 | B3: مقدمة وقرارات عامة | C3: قرار المنتج والتنفيذ | E3: الدردشة تُبنى كنواة مستقلة؛ تعطل أو فصل AI أو المحفظة أو الخدمات لا يجوز أن يوقف الرسائل والملفات والمجموعات والمكالمات ووظائف الدردشة الأساسية. | G3: أخضر — خلص | H3: ✅ خلص | I3: 2026-10-11 | J3: الشات
A4: 3 | B4: مقدمة وقرارات عامة | C4: قرار المنتج والتنفيذ | E4: DORR AI محرك مركزي واحد. لا يُبنى محرك AI ثانٍ داخل الدردشة، وأي استخدام لمحتوى محادثة مشفرة مع AI يكون بإجراء صريح من المستخدم وضمن النطاق الذي اختاره فقط. | G4: أخضر — خلص | H4: ✅ خلص | I4: 2026-10-11 | J4: الشات
A5: 4 | B5: مقدمة وقرارات عامة | C5: جاهزية الاشتراكات المستقبلية — بدون فرض اشتراك الآن | D5: 1 | E5: المرحلة الحالية: لا يُفترض إغلاق مزايا الدردشة خلف اشتراك لمجرد وجود هذه الوثيقة. الهدف الآن هو تعريف المستخدمين بقوة المنتج وبناء الاعتماد والاستخدام. | G5: أخضر — خلص | H5: ✅ خلص | I5: 2026-10-11 | J5: الشات
A6: 5 | B6: مقدمة وقرارات عامة | C6: جاهزية الاشتراكات المستقبلية — بدون فرض اشتراك الآن | D6: 2 | E6: من اليوم الأول يجب أن تكون البنية Subscription-Ready وEntitlement-Ready حتى تستطيع الإدارة مستقبلًا تحويل بعض القدرات أو السعات أو الخدمات الإضافية إلى خطط مدفوعة من لوحة التشغيل، من دون إعادة بناء التطبيقات. | G6: أصفر — مستني نظام تاني | H6: 🟠 مستني نظام تاني | I6: 2026-10-11 | J6: الشات | K6: مستني محرك الطلبات والخدمات المركزي (Order / Service Orchestrator)
A7: 6 | B7: مقدمة وقرارات عامة | C7: جاهزية الاشتراكات المستقبلية — بدون فرض اشتراك الآن | D7: 3 | E7: أي ميزة قابلة للتسييل مستقبلًا تُعامل تقنيًا كـ configurable entitlement وليست شرطًا أن تكون مدفوعة عند الإطلاق. القرار التجاري النهائي — مجاني/مدفوع/حد استخدام/دولة/فئة/حملة — يبقى Server-configurable. | G7: أصفر — مستني نظام تاني | H7: 🟠 مستني نظام تاني | I7: 2026-10-11 | J7: الشات | K7: مستني محرك الطلبات والخدمات المركزي (Order / Service Orchestrator)
A8: 7 | B8: مقدمة وقرارات عامة | C8: جاهزية الاشتراكات المستقبلية — بدون فرض اشتراك الآن | D8: 4 | E8: يُمنع Hard-code للأسعار أو أسماء الخطط أو حدود الاستخدام أو قائمة المزايا المدفوعة داخل Android/iOS/Vue. التطبيقات تعرض ما يعيده Backend من Plan Catalog وEntitlements وFeature Flags. | G8: أخضر — خلص | H8: ✅ خلص | I8: 2026-10-11 | J8: الشات
A9: 8 | B9: مقدمة وقرارات عامة | C9: جاهزية الاشتراكات المستقبلية — بدون فرض اشتراك الآن | D9: 5 | E9: يجب دعم حالات: Free، Trial، Paid، Promotional Access، Grace Period، Expired، وGrandfathered عند اعتمادها لاحقًا، مع عدم تعطيل Chat Core الأساسي بسبب مشكلة فوترة. | G9: أزرق — لسه | H9: 🔵 لسه — ممكن يتعمل | I9: 2026-10-11 | J9: الشات
A10: 9 | B10: مقدمة وقرارات عامة | C10: جاهزية الاشتراكات المستقبلية — بدون فرض اشتراك الآن | D10: 6 | E10: DORR AI يحتفظ بهيكل الاشتراكات المرجعي الوارد في وثيقته، لكن الأسعار والحدود المذكورة هناك مرجعية للتصميم وقابلة للتغيير إداريًا حسب الدولة والعملة والفئة. | G10: أخضر — خلص | H10: ✅ خلص | I10: 2026-10-11 | J10: الشات
A11: 10 | B11: مقدمة وقرارات عامة | C11: جاهزية الاشتراكات المستقبلية — بدون فرض اشتراك الآن | D11: 7 | E11: لا يضع المصمم شارات Premium على ميزة إلا إذا أعاد الخادم تصنيفها كذلك. ويمكن إظهار مزايا مستقبلية بصيغة «قريبًا» أو «متاحة لاحقًا» بقرار من الإدارة، دون وعد بسعر أو تاريخ إطلاق غير معتمد. | G11: أزرق — لسه | H11: 🔵 لسه — ممكن يتعمل | I11: 2026-10-11 | J11: الشات
A12: 11 | B12: مقدمة وقرارات عامة | C12: جاهزية الاشتراكات المستقبلية — بدون فرض اشتراك الآن | E12: Chat Core | F12: أساسي ومستقل | لا يتوقف بسبب الاشتراك أو AI | G12: أخضر — خلص | H12: ✅ خلص | I12: 2026-10-11 | J12: الشات
A13: 12 | B13: مقدمة وقرارات عامة | C13: جاهزية الاشتراكات المستقبلية — بدون فرض اشتراك الآن | E13: DORR AI | F13: تكامل مركزي | خطط/سعات عبر Entitlements | G13: أخضر — خلص | H13: ✅ خلص | I13: 2026-10-11 | J13: الشات
A14: 13 | B14: مقدمة وقرارات عامة | C14: جاهزية الاشتراكات المستقبلية — بدون فرض اشتراك الآن | E14: Moments / Discover / Sports / Calendar | F14: تُطلق حسب خطة المنتج | قابلة لتحديد سعات أو مزايا إضافية مستقبلًا | G14: أخضر — خلص | H14: ✅ خلص | I14: 2026-10-11 | J14: الشات
A15: 14 | B15: مقدمة وقرارات عامة | C15: جاهزية الاشتراكات المستقبلية — بدون فرض اشتراك الآن | E15: الأسعار والحدود | F15: لا Hard-code | Server-configurable حسب الدولة والعملة | G15: أخضر — خلص | H15: ✅ خلص | I15: 2026-10-11 | J15: الشات
A16: 15 | B16: مقدمة وقرارات عامة | C16: جاهزية الاشتراكات المستقبلية — بدون فرض اشتراك الآن | E16: المصمم | F16: واجهات واضحة وغير مضللة | حالات Free/Trial/Paid/Coming Soon من الخادم | G16: أزرق — لسه | H16: 🔵 لسه — ممكن يتعمل | I16: 2026-10-11 | J16: الشات
A17: 16 | B17: مقدمة وقرارات عامة | C17: الجزء الثالث — DORR AI: 367 بندًا/قدرة موثقة، بما فيها ضوابط HIGH STAKES، Quality Gate، وهيكل الاشتراكات المرجعي. | E17: قاعدة القراءة: عند وجود بند تكامل في الدردشة مع AI أو Wallet أو Service/Order Orchestrator، يبقى النظام المركزي المختص هو مصدر الحقيقة ولا يُنسخ منطقه داخل Chat Core. | G17: أخضر — خلص | H17: ✅ خلص | I17: 2026-10-11 | J17: الشات
A18: 17 | B18: الجزء الأول — نواة الدردشة والتكامل (1–97) | C18: النواة المستقلة + طبقة التكامل مع DORR + ملحق Backlog المستقبلي | E18: قرار معماري حاكم: الهدف المعماري: تُبنى خدمة الدردشة كنواة مستقلة قابلة للعمل بذاتها من اليوم الأول. أي اعتماد على محفظة دُرر أو DORR AI أو الحساب الموحد أو الخدمات أو السلوك/السمعة يوضع حصراً في طبقة تكامل منفصلة. إزالة طبقة التكامل مستقبلًا يجب ألا توقف الرسائل أو الملفات أو المجموعات أو المكالمات أو وظائف الدردشة الأساسية. | G18: أزرق — لسه | H18: 🔵 لسه — ممكن يتعمل | I18: 2026-10-11 | J18: الشات | K18: قاعدة أو مبدأ معماري مش ميزة لوحدها، ولسه ماتعلّمش عليه إنه اتحقق بالكامل
A19: 18 | B19: الجزء الأول — نواة الدردشة والتكامل (1–97) | C19: ضابطا الأمان الإلزاميان قبل أي تنفيذ | E19: أمان 1 — موافقة تسجيل المكالمات: يُمنع بدء تسجيل أي مكالمة صوتية أو مرئية إلا بعد موافقة صريحة ومباشرة من جميع الأطراف المشاركين في المكالمة. إذا رفض أي طرف أو لم يمنح الموافقة، لا يبدأ التسجيل. ويظهر مؤشر واضح طوال مدة التسجيل. | G19: أخضر — خلص | H19: ✅ خلص | I19: 2026-10-11 | J19: الشات
A20: 19 | B20: الجزء الأول — نواة الدردشة والتكامل (1–97) | C20: ضابطا الأمان الإلزاميان قبل أي تنفيذ | E20: أمان 2 — Feature Flag للمكالمات: مكالمات الصوت والفيديو تخضع لـ Feature Flag مستقل على مستوى الدولة/المدينة/الفئة. لا تُفعّل في أي دولة قبل تحقق إداري موثق من متطلبات الترخيص والتنظيم المحلي، وعند التعطيل تبقى بقية نواة الدردشة عاملة. | G20: أخضر — خلص | H20: ✅ خلص | I20: 2026-10-11 | J20: الشات
A21: 20 | B21: الجزء الأول — نواة الدردشة والتكامل (1–97) | C21: الجزء أ — نواة الدردشة المستقلة | E21: تعريف الجزء أ: هذا الجزء لا يعتمد على أي خدمة أخرى من دُرر. يجب أن يعمل كتطبيق مراسلة مستقل: رسائل نصية، تشفير، ملفات ووسائط، تنظيم محادثات، تنسيق نصوص، خصوصية، مجموعات، مكالمات، تخزين، بحث، ومزايا تجربة المستخدم. | G21: أزرق — لسه | H21: 🔵 لسه — ممكن يتعمل | I21: 2026-10-11 | J21: الشات | K21: قاعدة أو مبدأ معماري مش ميزة لوحدها، ولسه ماتعلّمش عليه إنه اتحقق بالكامل
A22: 21 | B22: الجزء الأول — نواة الدردشة والتكامل (1–97) | C22: أ.1 — قرار التشفير ومعالجة الذكاء الاصطناعي | E22: قرار صريح للبند 12: التشفير التام E2EE هو الوضع الافتراضي بين أطراف المحادثة. لا يطّلع DORR AI تلقائيًا على محتوى الرسائل المشفرة. عندما يطلب المستخدم صراحةً وظيفة AI على رسالة أو جزء من محادثة، يتم فك المحتوى المختار محليًا على جهاز المستخدم ثم تُرسل نسخة محددة فقط إلى DORR AI عبر قناة نقل مشفرة. تلك النسخة المرسلة إلى AI تكون خارج نطاق E2EE لهذه العملية فقط، ويجب إظهار ذلك للمستخدم قبل الإرسال. لا يجوز وصف الرسالة المختارة بأنها E2EE بالنسبة إلى معالجة AI بعد إرسالها إلى خدمة AI. | G22: أزرق — لسه | H22: ⏸ مؤجل بقرار | I22: 2026-10-11 | J22: الشات | K22: مؤجل بقرار: E2EE كوضع افتراضي (السبب في آخر docs/remaining_chat.md)
A23: 22 | B23: الجزء الأول — نواة الدردشة والتكامل (1–97) | C23: أ.1 — قرار التشفير ومعالجة الذكاء الاصطناعي | E23: قيد خصوصية: لا يجوز كسر E2EE أو نسخ محادثة كاملة إلى خوادم AI في الخلفية بغرض الاقتراحات أو التلخيص دون إجراء صريح من المستخدم وسياسة موافقة واضحة. | G23: أخضر — خلص | H23: ✅ خلص | I23: 2026-10-11 | J23: الشات
A24: 23 | B24: الجزء الأول — نواة الدردشة والتكامل (1–97) | C24: إدارة المحادثات المتقدمة | D24: 1 | E24: تصنيف المحادثات بألوان وتسميات | F24: تصنيف المحادثات بألوان مختلفة وتسميات مخصصة للتنظيم السريع. | G24: أخضر — خلص | H24: ✅ خلص | I24: 2026-10-11 | J24: الشات
A25: 24 | B25: الجزء الأول — نواة الدردشة والتكامل (1–97) | C25: إدارة المحادثات المتقدمة | D25: 2 | E25: وضع القراءة لاحقاً | F25: وضع علامة على رسائل لقراءتها لاحقاً دون فتحها الآن. | G25: أخضر — خلص | H25: ✅ خلص | I25: 2026-10-11 | J25: الشات
A26: 25 | B26: الجزء الأول — نواة الدردشة والتكامل (1–97) | C26: إدارة المحادثات المتقدمة | D26: 3 | E26: تخصيص نغمة لكل محادثة | F26: تعيين نغمة إشعار مختلفة لكل محادثة أو جهة اتصال. | G26: أخضر — خلص | H26: ✅ خلص | I26: 2026-10-11 | J26: الشات
A27: 26 | B27: الجزء الأول — نواة الدردشة والتكامل (1–97) | C27: إدارة المحادثات المتقدمة | D27: 4 | E27: تغيير خلفية المحادثة | F27: تغيير خلفية كل محادثة بصورة مخصصة أو لون مختلف. | G27: أخضر — خلص | H27: ✅ خلص | I27: 2026-10-11 | J27: الشات
A28: 27 | B28: الجزء الأول — نواة الدردشة والتكامل (1–97) | C28: إدارة المحادثات المتقدمة | D28: 5 | E28: تغيير ألوان فقاعات الشات | F28: تخصيص ألوان فقاعات الرسائل لكل محادثة بشكل مستقل. | G28: أخضر — خلص | H28: ✅ خلص | I28: 2026-10-11 | J28: الشات
A29: 28 | B29: الجزء الأول — نواة الدردشة والتكامل (1–97) | C29: إدارة المحادثات المتقدمة | D29: 6 | E29: تخصيص واجهة الدردشة بالكامل | F29: تخصيص كامل لواجهة الشات: خطوط، ألوان، أحجام، تخطيطات. | G29: أخضر — خلص | H29: ✅ خلص | I29: 2026-10-11 | J29: الشات
A30: 29 | B30: الجزء الأول — نواة الدردشة والتكامل (1–97) | C30: إدارة المحادثات المتقدمة | D30: 7 | E30: إعادة إرسال الرسائل الفاشلة تلقائياً | F30: إعادة إرسال الرسائل التي فشل تسليمها تلقائياً عند عودة الاتصال. | G30: أخضر — خلص | H30: ✅ خلص | I30: 2026-10-11 | J30: الشات
A31: 30 | B31: الجزء الأول — نواة الدردشة والتكامل (1–97) | C31: إدارة المحادثات المتقدمة | D31: 8 | E31: حفظ مسودة الرسالة تلقائياً عند الخروج | F31: حفظ ما كتبته تلقائياً عند مغادرة المحادثة للعودة إليه لاحقاً. | G31: أخضر — خلص | H31: ✅ خلص | I31: 2026-10-11 | J31: الشات
A32: 31 | B32: الجزء الأول — نواة الدردشة والتكامل (1–97) | C32: مشاركة الوسائط المتقدمة | D32: 9 | E32: إرسال ملفات حتى 10 جيجابايت | F32: رفع وإرسال ملفات ضخمة تصل إلى 10GB دفعة واحدة. | G32: أحمر — مش هيتعمل | H32: 🔴 مش هيتعمل | I32: 2026-10-11 | J32: الشات | K32: تكلفة تخزين كبيرة. الحد الحالي من الأدمن (لحد 2 جيجا)
A33: 32 | B33: الجزء الأول — نواة الدردشة والتكامل (1–97) | C33: مشاركة الوسائط المتقدمة | D33: 10 | E33: إرسال مجلدات كاملة | F33: إرسال مجلد بأكمله يحتوي على ملفات متعددة في عملية واحدة. | G33: أخضر — خلص | H33: ✅ خلص | I33: 2026-10-11 | J33: الشات
A34: 33 | B34: الجزء الأول — نواة الدردشة والتكامل (1–97) | C34: مشاركة الوسائط المتقدمة | D34: 11 | E34: تحويل الفيديو إلى GIF داخل الشات | F34: تحويل مقطع فيديو قصير إلى صورة GIF متحركة مباشرة داخل التطبيق. | G34: أخضر — خلص | H34: ✅ خلص | I34: 2026-10-11 | J34: الشات
A35: 34 | B35: الجزء الأول — نواة الدردشة والتكامل (1–97) | C35: مشاركة الوسائط المتقدمة | D35: 12 | E35: تسجيل الشاشة وإرسالها مباشرة | F35: تسجيل شاشة الهاتف وإرسال التسجيل مباشرة إلى المحادثة. | G35: أحمر — مش هيتعمل | H35: 🔴 مش هيتعمل | I35: 2026-10-11 | J35: الشات | K35: الموبايل نفسه بيعمل تسجيل الشاشة
A36: 35 | B36: الجزء الأول — نواة الدردشة والتكامل (1–97) | C36: مشاركة الوسائط المتقدمة | D36: 13 | E36: ضغط الصور تلقائياً حسب الاتصال | F36: ضغط الصور تلقائياً عند الاتصال البطيء وإرسالها بجودة كاملة عند السريع. | G36: أخضر — خلص | H36: ✅ خلص | I36: 2026-10-11 | J36: الشات
A37: 36 | B37: الجزء الأول — نواة الدردشة والتكامل (1–97) | C37: مشاركة الوسائط المتقدمة | D37: 14 | E37: مشاركة ألبومات الصور كاملة | F37: إرسال مجموعة صور كألبوم متكامل مع عرض شرائح تفاعلي. | G37: أخضر — خلص | H37: ✅ خلص | I37: 2026-10-11 | J37: الشات
A38: 37 | B38: الجزء الأول — نواة الدردشة والتكامل (1–97) | C38: مشاركة الوسائط المتقدمة | D38: 15 | E38: معاينة المستندات داخل الشات | F38: معاينة محتوى ملفات PDF والمستندات مباشرة دون تنزيل. | G38: أخضر — خلص | H38: ✅ خلص | I38: 2026-10-11 | J38: الشات
A39: 38 | B39: الجزء الأول — نواة الدردشة والتكامل (1–97) | C39: مشاركة الوسائط المتقدمة | D39: 16 | E39: تشغيل الفيديو داخل المحادثة | F39: تشغيل مقاطع الفيديو داخل نافذة الدردشة مباشرة بدون خروج. | G39: أخضر — خلص | H39: ✅ خلص | I39: 2026-10-11 | J39: الشات
A40: 39 | B40: الجزء الأول — نواة الدردشة والتكامل (1–97) | C40: البحث والتصفية المتقدمة | D40: 17 | E40: البحث في الصور داخل المحادثة | F40: البحث في الصور المشتركة داخل المحادثة بالكلمات أو التاريخ. | G40: أخضر — خلص | H40: ✅ خلص | I40: 2026-10-11 | J40: الشات
A41: 40 | B41: الجزء الأول — نواة الدردشة والتكامل (1–97) | C41: البحث والتصفية المتقدمة | D41: 18 | E41: البحث في الملفات داخل المحادثة | F41: تصفية وعرض الملفات المشتركة في المحادثة حسب النوع والحجم. | G41: أخضر — خلص | H41: ✅ خلص | I41: 2026-10-11 | J41: الشات
A42: 41 | B42: الجزء الأول — نواة الدردشة والتكامل (1–97) | C42: البحث والتصفية المتقدمة | D42: 19 | E42: البحث في الروابط المشتركة | F42: عرض جميع الروابط التي تمت مشاركتها في محادثة معينة. | G42: أخضر — خلص | H42: ✅ خلص | I42: 2026-10-11 | J42: الشات
A43: 42 | B43: الجزء الأول — نواة الدردشة والتكامل (1–97) | C43: البحث والتصفية المتقدمة | D43: 20 | E43: البحث في الرسائل الصوتية | F43: البحث داخل الرسائل الصوتية بالكلمات المفتاحية (نصّ تلقائي). | G43: أخضر — خلص | H43: ✅ خلص | I43: 2026-10-11 | J43: الشات
A44: 43 | B44: الجزء الأول — نواة الدردشة والتكامل (1–97) | C44: البحث والتصفية المتقدمة | D44: 21 | E44: فلترة الرسائل حسب النوع | F44: تصفية رسائل المحادثة: نصية فقط / صور / فيديو / ملفات / صوت. | G44: أخضر — خلص | H44: ✅ خلص | I44: 2026-10-11 | J44: الشات
A45: 44 | B45: الجزء الأول — نواة الدردشة والتكامل (1–97) | C45: البحث والتصفية المتقدمة | D45: 22 | E45: عرض الوسائط في معرض منظم | F45: عرض جميع الصور والفيديوهات المشتركة في معرض منظم بالتاريخ. | G45: أخضر — خلص | H45: ✅ خلص | I45: 2026-10-11 | J45: الشات
A46: 45 | B46: الجزء الأول — نواة الدردشة والتكامل (1–97) | C46: البحث والتصفية المتقدمة | D46: 23 | E46: تصنيف الوسائط حسب النوع | F46: فصل الصور والفيديوهات والمستندات الصوتية في أقسام مختلفة. | G46: أخضر — خلص | H46: ✅ خلص | I46: 2026-10-11 | J46: الشات
A47: 46 | B47: الجزء الأول — نواة الدردشة والتكامل (1–97) | C47: البحث والتصفية المتقدمة | D47: 24 | E47: حفظ الرسائل المهمة في مجلد خاص | F47: حفظ رسائل في مجلد 'المفضلة' مستقل عن قائمة النجوم. | G47: أخضر — خلص | H47: ✅ خلص | I47: 2026-10-11 | J47: الشات
... A49: 48 | B49: الجزء الأول — نواة الدردشة والتكامل (1–97) | C49: الأمان المتقدم | D49: 26 | E49: منع تصوير الشاشة في المحادثات العادية | F49: منع لقطات الشاشة في أي محادثة وليس فقط وسائط 'مرة واحدة'. | G49: أخضر — خلص | H49: ✅ خلص | I49: 2026-10-11 | J49: الشات
A50: 49 | B50: الجزء الأول — نواة الدردشة والتكامل (1–97) | C50: الأمان المتقدم | D50: 27 | E50: تنبيه محاولات الاختراق | F50: إشعار فوري عند اكتشاف أي محاولة وصول غير مصرح بها للحساب. | G50: أصفر — مستني نظام تاني | H50: 🟠 مستني نظام تاني | I50: 2026-10-11 | J50: الشات | K50: على مستوى الحساب كله (أمان الحساب) — مش شغل شات
A51: 50 | B51: الجزء الأول — نواة الدردشة والتكامل (1–97) | C51: الأمان المتقدم | D51: 28 | E51: سجل الأمان الكامل | F51: سجل مفصل بجميع أنشطة تسجيل الدخول والأجهزة المستخدمة. | G51: أصفر — مستني نظام تاني | H51: 🟠 مستني نظام تاني | I51: 2026-10-11 | J51: الشات | K51: على مستوى الحساب كله (أمان الحساب) — مش شغل شات
A52: 51 | B52: الجزء الأول — نواة الدردشة والتكامل (1–97) | C52: الأمان المتقدم | D52: 29 | E52: إدارة الأجهزة وتسجيل الخروج منها | F52: رؤية جميع الأجهزة المتصلة بالحساب وتسجيل الخروج منها فوراً. | G52: أصفر — مستني نظام تاني | H52: 🟠 مستني نظام تاني | I52: 2026-10-11 | J52: الشات | K52: على مستوى الحساب كله (أمان الحساب) — مش شغل شات
A53: 52 | B53: الجزء الأول — نواة الدردشة والتكامل (1–97) | C53: الأمان المتقدم | D53: 30 | E53: حماية النسخ الاحتياطي المحلي | F53: حماية النسخ الاحتياطي المحفوظة على الجهاز بكلمة مرور منفصلة. | G53: أحمر — مش هيتعمل | H53: 🔴 مش هيتعمل | I53: 2026-10-11 | J53: الشات | K53: مفيش نسخة احتياطية محلية أصلاً
A54: 53 | B54: الجزء الأول — نواة الدردشة والتكامل (1–97) | C54: الموقع الجغرافي — قدرات مستقلة داخل النواة | D54: 72 | E54: مشاركة الموقع المباشر (Live Location) | F54: مشاركة الموقع الحالي المتحرك في الوقت الفعلي مع تحديث مستمر. | G54: أخضر — خلص | H54: ✅ خلص | I54: 2026-10-11 | J54: الشات
A55: 54 | B55: الجزء الأول — نواة الدردشة والتكامل (1–97) | C55: الموقع الجغرافي — قدرات مستقلة داخل النواة | D55: 74 | E55: إرسال الموقع التفاعلي | F55: إرسال خريطة تفاعلية يمكن للمستلم التنقل فيها وتكبيرها. | G55: أصفر — مستني نظام تاني | H55: 🟠 مستني نظام تاني | I55: 2026-10-11 | J55: الشات | K55: محتاج مزود خرايط وأماكن (Google Maps / Places)
A56: 55 | B56: الجزء الأول — نواة الدردشة والتكامل (1–97) | C56: الموقع الجغرافي — قدرات مستقلة داخل النواة | D56: 78 | E56: إرسال أماكن قريبة مقترحة | F56: اقتراح مطاعم أو متاجر أو خدمات قريبة من الموقع وإرسالها. | G56: أصفر — مستني نظام تاني | H56: 🟠 مستني نظام تاني | I56: 2026-10-11 | J56: الشات | K56: محتاج مزود خرايط وأماكن (Google Maps / Places)
A57: 56 | B57: الجزء الأول — نواة الدردشة والتكامل (1–97) | C57: الموقع الجغرافي — قدرات مستقلة داخل النواة | D57: 79 | E57: مشاركة خرائط تفاعلية كاملة | F57: مشاركة خرائط مع مسارات ونقاط اهتمام متعددة محددة سلفاً. | G57: أصفر — مستني نظام تاني | H57: 🟠 مستني نظام تاني | I57: 2026-10-11 | J57: الشات | K57: محتاج مزود خرايط وأماكن (Google Maps / Places)
A58: 57 | B58: الجزء الأول — نواة الدردشة والتكامل (1–97) | C58: الموقع الجغرافي — قدرات مستقلة داخل النواة | D58: 80 | E58: التنقل إلى الموقع من الشات | F58: فتح التنقل مباشرة إلى موقع مشارَك بنقرة واحدة من المحادثة. | G58: أخضر — خلص | H58: ✅ خلص | I58: 2026-10-11 | J58: الشات
A59: 58 | B59: الجزء الأول — نواة الدردشة والتكامل (1–97) | C59: تجربة المستخدم والأداء — قدرات مستقلة | D59: 81 | E59: استخدام معرف (Username) بدل رقم الهاتف | F59: التواصل مع الآخرين باسم مستعار دون الكشف عن رقم الهاتف. | G59: أخضر — خلص | H59: ✅ خلص | I59: 2026-10-11 | J59: الشات
A60: 59 | B60: الجزء الأول — نواة الدردشة والتكامل (1–97) | C60: تجربة المستخدم والأداء — قدرات مستقلة | D60: 82 | E60: وضع توفير البيانات الذكي | F60: تقليل استهلاك الإنترنت تلقائياً مع الحفاظ على جودة المحادثة. | G60: أخضر — خلص | H60: ✅ خلص | I60: 2026-10-11 | J60: الشات
A61: 60 | B61: الجزء الأول — نواة الدردشة والتكامل (1–97) | C61: تجربة المستخدم والأداء — قدرات مستقلة | D61: 83 | E61: إحصائيات الاستخدام الشخصية | F61: عرض تقارير عن وقت الاستخدام وعدد الرسائل والخدمات المستخدمة. | G61: أخضر — خلص | H61: ✅ خلص | I61: 2026-10-11 | J61: الشات
A62: 61 | B62: الجزء الأول — نواة الدردشة والتكامل (1–97) | C62: تجربة المستخدم والأداء — قدرات مستقلة | D62: 84 | E62: اقتراح الأصدقاء بناءً على الاهتمامات | F62: اقتراح جهات اتصال جديدة بناءً على الاهتمامات المشتركة. | G62: أحمر — مش هيتعمل | H62: 🔴 مش هيتعمل | I62: 2026-10-11 | J62: الشات | K62: خطر على الخصوصية
A63: 62 | B63: الجزء الأول — نواة الدردشة والتكامل (1–97) | C63: تجربة المستخدم والأداء — قدرات مستقلة | D63: 87 | E63: تحسين الأداء للهواتف الضعيفة | F63: وضع خفيف خاص للهواتف ذات موارد محدودة يوفر 50% من الحجم. | G63: أخضر — خلص | H63: ✅ خلص | I63: 2026-10-11 | J63: الشات
A64: 63 | B64: الجزء الأول — نواة الدردشة والتكامل (1–97) | C64: تجربة المستخدم والأداء — قدرات مستقلة | D64: 88 | E64: إرسال رسائل بدون إشعار صوتي (Silent) | F64: إرسال رسالة مع تحديد عدم إصدار أي صوت إشعار للمستلم. | G64: أخضر — خلص | H64: ✅ خلص | I64: 2026-10-11 | J64: الشات
A65: 64 | B65: الجزء الأول — نواة الدردشة والتكامل (1–97) | C65: تجربة المستخدم والأداء — قدرات مستقلة | D65: 89 | E65: واجهة تفاعلية متكيفة مع الجهاز | F65: الواجهة تتكيف تلقائياً مع حجم الشاشة ونوع الجهاز ودقة العرض. | G65: أخضر — خلص | H65: ✅ خلص | I65: 2026-10-11 | J65: الشات
A66: 65 | B66: الجزء الأول — نواة الدردشة والتكامل (1–97) | C66: تجربة المستخدم والأداء — قدرات مستقلة | D66: 90 | E66: تخصيص الحالة الشخصية المتقدمة | F66: إعداد حالة مفصلة مع أيقونات ومدة زمنية وجمهور مخصص. | G66: أخضر — خلص | H66: ✅ خلص | I66: 2026-10-11 | J66: الشات
A67: 66 | B67: الجزء الأول — نواة الدردشة والتكامل (1–97) | C67: الصوت والفيديو المتقدم | D67: 91 | E67: غرف صوتية دائمة (Voice Rooms) | F67: إنشاء غرف صوتية تبقى مفتوحة دائماً يدخلها ويخرجها الأعضاء بحرية. | G67: أخضر — خلص | H67: ✅ خلص | I67: 2026-10-11 | J67: الشات
A68: 67 | B68: الجزء الأول — نواة الدردشة والتكامل (1–97) | C68: الصوت والفيديو المتقدم | D68: 92 | E68: تسجيل المكالمات | F68: تسجيل المكالمات الصوتية والمرئية فقط بعد موافقة صريحة من جميع الأطراف؛ لا يبدأ التسجيل عند رفض أو غياب موافقة أي طرف، ويظهر مؤشر تسجيل واضح طوال المدة. | G68: أخضر — خلص | H68: ✅ خلص | I68: 2026-10-11 | J68: الشات
A69: 68 | B69: الجزء الأول — نواة الدردشة والتكامل (1–97) | C69: الصوت والفيديو المتقدم | D69: 93 | E69: تحويل المكالمة إلى بث مباشر | F69: تحويل مكالمة جماعية إلى بث مباشر يشاهده عدد غير محدود. | G69: أخضر — خلص | H69: ✅ خلص | I69: 2026-10-11 | J69: الشات
A70: 69 | B70: الجزء الأول — نواة الدردشة والتكامل (1–97) | C70: الصوت والفيديو المتقدم | D70: 94 | E70: تأثيرات الكاميرا الافتراضية | F70: تأثيرات وخلفيات افتراضية وضبابية أثناء مكالمة الفيديو. | G70: أخضر — خلص | H70: ✅ خلص | I70: 2026-10-11 | J70: الشات
A71: 70 | B71: الجزء الأول — نواة الدردشة والتكامل (1–97) | C71: الصوت والفيديو المتقدم | D71: 95 | E71: تبديل الكاميرا الأمامية والخلفية | F71: التبديل بين الكاميرا الأمامية والخلفية بسهولة أثناء المكالمة. | G71: أخضر — خلص | H71: ✅ خلص | I71: 2026-10-11 | J71: الشات
A72: 71 | B72: الجزء الأول — نواة الدردشة والتكامل (1–97) | C72: إدارة المجموعات المتقدمة | D72: 96 | E72: وضع Slow Mode لتقليل الرسائل | F72: تحديد الحد الأدنى للوقت بين رسائل العضو الواحد في المجموعة. | G72: أخضر — خلص | H72: ✅ خلص | I72: 2026-10-11 | J72: الشات
A73: 72 | B73: الجزء الأول — نواة الدردشة والتكامل (1–97) | C73: إدارة المجموعات المتقدمة | D73: 97 | E73: فلترة الكلمات المحظورة تلقائياً | F73: حذف الرسائل التي تحتوي على كلمات محظورة تلقائياً قبل نشرها. | G73: أخضر — خلص | H73: ✅ خلص | I73: 2026-10-11 | J73: الشات
A74: 73 | B74: الجزء الأول — نواة الدردشة والتكامل (1–97) | C74: إدارة المجموعات المتقدمة | E74: قيد تشغيل: وظائف المكالمات الواردة في هذا الجزء جزء من النواة تقنيًا، لكن تفعيلها التشغيلي يخضع دائمًا لـ Feature Flag الخاص بكل دولة وفق ضابط الأمان أعلاه. | G74: أخضر — خلص | H74: ✅ خلص | I74: 2026-10-11 | J74: الشات
A75: 74 | B75: الجزء الأول — نواة الدردشة والتكامل (1–97) | C75: الجزء ب — نقاط التكامل مع دُرر | E75: تعريف الجزء ب: هذه طبقة ربط منفصلة فوق النواة وليست جزءًا من محرك الدردشة نفسه. كل تكامل يجب أن يكون خلف Interface/API واضح وقابل للاستبدال. عند إزالة هذه الطبقة تبقى النواة في الجزء أ عاملة دون إعادة بناء. | G75: أزرق — لسه | H75: 🔵 لسه — ممكن يتعمل | I75: 2026-10-11 | J75: الشات | K75: قاعدة أو مبدأ معماري مش ميزة لوحدها، ولسه ماتعلّمش عليه إنه اتحقق بالكامل
A76: 75 | B76: الجزء الأول — نواة الدردشة والتكامل (1–97) | C76: ب.1 — الهوية والحساب الموحد | E76: قاعدة إلزامية: تستخدم الدردشة نفس نظام الحساب الموحد لدُرر (فرد / رب أسرة / شركة) ولا تنشئ نظام هوية أو قاعدة حسابات مستقلة خاصة بالدردشة. تصل الدردشة فقط إلى الحد الأدنى من بيانات الهوية والصلاحيات اللازمة عبر Account/Identity API. | G76: أخضر — خلص | H76: ✅ خلص | I76: 2026-10-11 | J76: الشات
A77: 76 | B77: الجزء الأول — نواة الدردشة والتكامل (1–97) | C77: ب.2 — مساعد DORR AI (البنود 31–51) | E77: قاعدة تكامل AI: كل البنود 31–51 تستدعي DORR AI عبر نفس الواجهة المعتمدة في وثيقة DORR AI. لا يُبنى محرك AI منفصل داخل الدردشة. وترث جميع استدعاءات الدردشة قواعد DORR AI 351–362 كاملة، وخاصة قواعد HIGH STAKES والتصنيف والإحالات الإلزامية وRiskClassifier وSafetyPolicyEngine وQuality Gate. | G77: أزرق — لسه | H77: ✅ خلص | I77: 2026-10-14 | J77: دُرر AI | K77: كل أدوات الـ AI في الشات بقت بتعدّي على AiTaskRunner (نفس نظام دُرر AI): التوجيه، والـ fallback، وقواعد الأمان، وحظر الأدمن، والتسجيل في لوحة الأدمن. والردود المقترحة بقت تحت قواعد 351–362. وبقت كلها مربوطة بباقات دُرر AI (ADR-013)
A78: 77 | B78: الجزء الأول — نواة الدردشة والتكامل (1–97) | C78: ب.2 — مساعد DORR AI (البنود 31–51) | D78: 31 | E78: مساعد AI داخل المحادثة | F78: مساعد ذكي داخل كل محادثة للإجابة على الأسئلة وتقديم اقتراحات. | G78: أخضر — خلص | H78: ✅ خلص | I78: 2026-10-11 | J78: دُرر AI
A79: 78 | B79: الجزء الأول — نواة الدردشة والتكامل (1–97) | C79: ب.2 — مساعد DORR AI (البنود 31–51) | D79: 32 | E79: اقتراح الردود الذكية حسب السياق | F79: اقتراح ردود مناسبة بناءً على محتوى الرسالة الواردة تلقائياً. | G79: أخضر — خلص | H79: ✅ خلص | I79: 2026-10-11 | J79: دُرر AI
A80: 79 | B80: الجزء الأول — نواة الدردشة والتكامل (1–97) | C80: ب.2 — مساعد DORR AI (البنود 31–51) | D80: 33 | E80: تلخيص المحادثات الطويلة | F80: تلخيص محادثة كاملة أو فترة زمنية محددة بنقرة واحدة. | G80: أخضر — خلص | H80: ✅ خلص | I80: 2026-10-11 | J80: دُرر AI
A81: 80 | B81: الجزء الأول — نواة الدردشة والتكامل (1–97) | C81: ب.2 — مساعد DORR AI (البنود 31–51) | D81: 34 | E81: تحويل الصوت إلى نص تلقائياً | F81: تحويل الرسائل الصوتية إلى نص مكتوب تلقائياً لسهولة القراءة. | G81: أخضر — خلص | H81: ✅ خلص | I81: 2026-10-11 | J81: دُرر AI
A82: 81 | B82: الجزء الأول — نواة الدردشة والتكامل (1–97) | C82: ب.2 — مساعد DORR AI (البنود 31–51) | D82: 35 | E82: ترجمة فورية للرسائل | F82: ترجمة أي رسالة فورياً إلى لغتك المفضلة بنقرة واحدة. | G82: أخضر — خلص | H82: ✅ خلص | I82: 2026-10-11 | J82: دُرر AI
A83: 82 | B83: الجزء الأول — نواة الدردشة والتكامل (1–97) | C83: ب.2 — مساعد DORR AI (البنود 31–51) | D83: 36 | E83: تصحيح الأخطاء الإملائية بالذكاء الاصطناعي | F83: اكتشاف وتصحيح الأخطاء الإملائية والنحوية قبل إرسال الرسالة. | G83: أخضر — خلص | H83: ✅ خلص | I83: 2026-10-11 | J83: دُرر AI
A84: 83 | B84: الجزء الأول — نواة الدردشة والتكامل (1–97) | C84: ب.2 — مساعد DORR AI (البنود 31–51) | D84: 37 | E84: تحليل نية الرسالة | F84: تحليل هدف الرسالة الواردة واقتراح الإجراء المناسب تلقائياً. | G84: أخضر — خلص | H84: ✅ خلص | I84: 2026-10-11 | J84: دُرر AI
A85: 84 | B85: الجزء الأول — نواة الدردشة والتكامل (1–97) | C85: ب.2 — مساعد DORR AI (البنود 31–51) | D85: 38 | E85: تحويل الرسائل إلى مهام | F85: تحويل رسالة تحتوي على طلب أو مهمة إلى قائمة مهام مرتبة. | G85: أخضر — خلص | H85: ✅ خلص | I85: 2026-10-11 | J85: دُرر AI
A86: 85 | B86: الجزء الأول — نواة الدردشة والتكامل (1–97) | C86: ب.2 — مساعد DORR AI (البنود 31–51) | D86: 39 | E86: إنشاء ملاحظات من الرسائل | F86: استخراج المعلومات المهمة من الرسائل وحفظها كملاحظات منظمة. | G86: أخضر — خلص | H86: ✅ خلص | I86: 2026-10-11 | J86: دُرر AI
A87: 86 | B87: الجزء الأول — نواة الدردشة والتكامل (1–97) | C87: ب.2 — مساعد DORR AI (البنود 31–51) | D87: 40 | E87: تذكير بالمواعيد من المحادثة | F87: اكتشاف المواعيد المذكورة في الرسائل وإضافتها تلقائياً كتذكيرات. | G87: أخضر — خلص | H87: ✅ خلص | I87: 2026-10-11 | J87: دُرر AI
A88: 87 | B88: الجزء الأول — نواة الدردشة والتكامل (1–97) | C88: ب.2 — مساعد DORR AI (البنود 31–51) | D88: 41 | E88: فلترة الرسائل المهمة بالذكاء الاصطناعي | F88: تصنيف الرسائل حسب الأهمية وإبراز ما يستحق الاهتمام. | G88: أخضر — خلص | H88: ✅ خلص | I88: 2026-10-11 | J88: دُرر AI
A89: 88 | B89: الجزء الأول — نواة الدردشة والتكامل (1–97) | C89: ب.2 — مساعد DORR AI (البنود 31–51) | D89: 42 | E89: تحليل المشاعر في الرسائل | F89: تحليل النبرة العاطفية في الرسائل واقتراح الرد المناسب. | G89: أخضر — خلص | H89: ✅ خلص | I89: 2026-10-11 | J89: دُرر AI
A90: 89 | B90: الجزء الأول — نواة الدردشة والتكامل (1–97) | C90: ب.2 — مساعد DORR AI (البنود 31–51) | D90: 43 | E90: اقتراح إجراءات تلقائية | F90: اقتراح إجراءات بناءً على الرسائل: حجز، دفع، إلغاء، تذكير. | G90: أصفر — مستني نظام تاني | H90: 🟠 مستني نظام تاني | I90: 2026-10-11 | J90: دُرر AI | K90: مستني محرك الطلبات والخدمات المركزي (Order / Service Orchestrator)
A91: 90 | B91: الجزء الأول — نواة الدردشة والتكامل (1–97) | C91: ب.2 — مساعد DORR AI (البنود 31–51) | D91: 44 | E91: مساعد حجز الخدمات | F91: مساعد ذكي يساعد على حجز الخدمات مباشرة من داخل الشات. | G91: أصفر — مستني نظام تاني | H91: 🟠 مستني نظام تاني | I91: 2026-10-11 | J91: دُرر AI | K91: مستني محرك الطلبات والخدمات المركزي (Order / Service Orchestrator)
A92: 91 | B92: الجزء الأول — نواة الدردشة والتكامل (1–97) | C92: ب.2 — مساعد DORR AI (البنود 31–51) | D92: 45 | E92: اقتراح أماكن قريبة حسب السياق | F92: اقتراح مطاعم أو خدمات قريبة بناءً على موضوع المحادثة. | G92: أصفر — مستني نظام تاني | H92: 🟠 مستني نظام تاني | I92: 2026-10-11 | J92: دُرر AI | K92: محتاج مزود خرايط وأماكن (Google Maps / Places)
A93: 92 | B93: الجزء الأول — نواة الدردشة والتكامل (1–97) | C93: ب.2 — مساعد DORR AI (البنود 31–51) | D93: 46 | E93: تحليل الرسائل الطويلة وتبسيطها | F93: تبسيط الرسائل الطويلة وعرض أبرز النقاط في ملخص قصير. | G93: أخضر — خلص | H93: ✅ خلص | I93: 2026-10-11 | J93: دُرر AI
A94: 93 | B94: الجزء الأول — نواة الدردشة والتكامل (1–97) | C94: ب.2 — مساعد DORR AI (البنود 31–51) | D94: 47 | E94: تحويل الرسائل إلى تذكيرات | F94: تحويل أي رسالة إلى تذكير بتاريخ ووقت محددين. | G94: أخضر — خلص | H94: ✅ خلص | I94: 2026-10-11 | J94: دُرر AI
A95: 94 | B95: الجزء الأول — نواة الدردشة والتكامل (1–97) | C95: ب.2 — مساعد DORR AI (البنود 31–51) | D95: 48 | E95: اقتراح ملفات مرتبطة بالمحادثة | F95: اقتراح ملفات أو مستندات سبق مشاركتها وتتعلق بالمحادثة الحالية. | G95: أخضر — خلص | H95: ✅ خلص | I95: 2026-10-11 | J95: دُرر AI
A96: 95 | B96: الجزء الأول — نواة الدردشة والتكامل (1–97) | C96: ب.2 — مساعد DORR AI (البنود 31–51) | D96: 49 | E96: تلخيص المحادثة اليومية | F96: تلخيص تلقائي لجميع محادثات اليوم مع أبرز الأحداث والقرارات. | G96: أخضر — خلص | H96: ✅ خلص | I96: 2026-10-11 | J96: دُرر AI
A97: 96 | B97: الجزء الأول — نواة الدردشة والتكامل (1–97) | C97: ب.2 — مساعد DORR AI (البنود 31–51) | D97: 50 | E97: توليد صور بالوصف النصي | F97: توليد صور بالذكاء الاصطناعي بناءً على وصف نصي وإرسالها في الشات. | G97: أحمر — مش هيتعمل | H97: ✅ خلص | I97: 2026-10-15 | J97: دُرر AI | K97: «صورة بالذكاء الاصطناعي» في قايمة المرفقات: معاينة، ثم إرسال كرسالة صورة عليها «بالذكاء الاصطناعي». بتتحسب من الصور اليومية في الباقة
A98: 97 | B98: الجزء الأول — نواة الدردشة والتكامل (1–97) | C98: ب.2 — مساعد DORR AI (البنود 31–51) | D98: 51 | E98: تحرير الصور بالذكاء الاصطناعي | F98: تحرير وتحسين الصور الموجودة باستخدام الذكاء الاصطناعي داخل التطبيق. | G98: أحمر — مش هيتعمل | H98: ✅ خلص | I98: 2026-10-15 | J98: دُرر AI | K98: «عدّلها بالذكاء الاصطناعي» على أي صورة في الشات: معاينة، ثم إرسال. نفس الباقة والحصة اليومية
A99: 98 | B99: الجزء الأول — نواة الدردشة والتكامل (1–97) | C99: ب.3 — الخدمات داخل الشات (البنود 52–61) | E99: قاعدة تكامل الخدمات: هذه البنود لا تنفذ منطق خدمات النقل أو الطعام أو الفنادق أو الطيران داخل الدردشة. الدردشة تستدعي Service Orchestrator/واجهات خدمات DORR وتعرض النتيجة والحالة فقط. | G99: أخضر — خلص | H99: ✅ خلص | I99: 2026-10-11 | J99: الشات
A100: 99 | B100: الجزء الأول — نواة الدردشة والتكامل (1–97) | C100: ب.3 — الخدمات داخل الشات (البنود 52–61) | D100: 52 | E100: طلب سيارة من الشات | F100: طلب سيارة توصيل مباشرة من داخل المحادثة دون مغادرة التطبيق. | G100: أصفر — مستني نظام تاني | H100: 🟠 مستني نظام تاني | I100: 2026-10-11 | J100: الشات | K100: مستني محرك الطلبات والخدمات المركزي (Order / Service Orchestrator)
A101: 100 | B101: الجزء الأول — نواة الدردشة والتكامل (1–97) | C101: ب.3 — الخدمات داخل الشات (البنود 52–61) | D101: 53 | E101: طلب طعام من الشات | F101: طلب وجبة من مطعم مباشرة من داخل المحادثة. | G101: أصفر — مستني نظام تاني | H101: 🟠 مستني نظام تاني | I101: 2026-10-11 | J101: الشات | K101: مستني محرك الطلبات والخدمات المركزي (Order / Service Orchestrator)
...

Sheet اتغير بعد الملف
A1: # | B1: الجزء | C1: القسم | D1: رقم البند | E1: البند | F1: الوصف | G1: الحالة في ملف الورد (2026-10-11) | H1: الحالة الحالية | I1: آخر تحديث | J1: يخص | K1: ملاحظات
A2: 1 | B2: الجزء الأول — نواة الدردشة والتكامل (1–97) | C2: ب.2 — مساعد DORR AI (البنود 31–51) | E2: قاعدة تكامل AI: كل البنود 31–51 تستدعي DORR AI عبر نفس الواجهة المعتمدة في وثيقة DORR AI. لا يُبنى محرك AI منفصل داخل الدردشة. وترث جميع استدعاءات الدردشة قواعد DORR AI 351–362 كاملة، وخاصة قواعد HIGH STAKES والتصنيف والإحالات الإلزامية وRiskClassifier وSafetyPolicyEngine وQuality Gate. | G2: أزرق — لسه | H2: ✅ خلص | I2: 2026-10-14 | J2: دُرر AI | K2: كل أدوات الـ AI في الشات بقت بتعدّي على AiTaskRunner (نفس نظام دُرر AI): التوجيه، والـ fallback، وقواعد الأمان، وحظر الأدمن، والتسجيل في لوحة الأدمن. والردود المقترحة بقت تحت قواعد 351–362. وبقت كلها مربوطة بباقات دُرر AI (ADR-013)
A3: 2 | B3: الجزء الأول — نواة الدردشة والتكامل (1–97) | C3: ب.2 — مساعد DORR AI (البنود 31–51) | D3: 50 | E3: توليد صور بالوصف النصي | F3: توليد صور بالذكاء الاصطناعي بناءً على وصف نصي وإرسالها في الشات. | G3: أحمر — مش هيتعمل | H3: ✅ خلص | I3: 2026-10-15 | J3: دُرر AI | K3: «صورة بالذكاء الاصطناعي» في قايمة المرفقات: معاينة، ثم إرسال كرسالة صورة عليها «بالذكاء الاصطناعي». بتتحسب من الصور اليومية في الباقة
A4: 3 | B4: الجزء الأول — نواة الدردشة والتكامل (1–97) | C4: ب.2 — مساعد DORR AI (البنود 31–51) | D4: 51 | E4: تحرير الصور بالذكاء الاصطناعي | F4: تحرير وتحسين الصور الموجودة باستخدام الذكاء الاصطناعي داخل التطبيق. | G4: أحمر — مش هيتعمل | H4: ✅ خلص | I4: 2026-10-15 | J4: دُرر AI | K4: «عدّلها بالذكاء الاصطناعي» على أي صورة في الشات: معاينة، ثم إرسال. نفس الباقة والحصة اليومية
A5: 4 | B5: الجزء الأول — نواة الدردشة والتكامل (1–97) | C5: قرارات حاكمة للمصمم — التمويل والهيدر | E5: نموذج التمويل — الدردشة مجانية بالكامل للمستخدم: لا يوجد اشتراك مدفوع للدردشة، ولا حد استخدام مدفوع، ولا تُصمَّم داخل نواة الدردشة أي شاشة «ترقية الحساب» أو «حصة الاستخدام». يتحقق دخل الدردشة حصراً عبر: (أ) رسوم محفظة دُرر المركزية على الحركة المالية المنفذة داخل الشات عبر Wallet API، وفق سياسة الرسوم المركزية المعتمدة ونفس آلية الرسوم المعتمدة بخدمة الوقود؛ و(ب) رسوم على مقدمي الخدمات/الشركات مقابل الوصول أو التواصل مع العميل عبر الدردشة. لا تُفرض رسوم اشتراك للدردشة على المستخدم النهائي. | G5: أصفر — مستني نظام تاني | H5: 🟡 جزئي | I5: 2026-10-15 | J5: الشات | K5: اتعدّل بقرار (ADR-013): نواة الشات فضلت مجانية، بس أدوات الـ AI فيه بقت محتاجة اشتراك في دُرر AI. الدعم الفني فضل مجاني
A6: 5 | B6: الجزء الأول — نواة الدردشة والتكامل (1–97) | C6: قرارات حاكمة للمصمم — التمويل والهيدر | E6: قاعدة الهيدر والملاحة — مرجع موحّد مع DORR AI: الشاشة الرئيسية للدردشة بلا سهم رجوع. في كل شاشة فرعية يكون سهم الرجوع في أقصى اليمين، ويكون شعار DORR إلى يساره مع اتجاه الرجوع الصحيح (→) وفق RTL. النوافذ السفلية Bottom Sheet تستخدم زر إغلاق ×. يُمنع ابتكار نمط هيدر أو ملاحة مستقل يخالف المرجع المعتمد في DORR AI. | G6: أزرق — لسه | H6: ✅ خلص | I6: 2026-10-11 | J6: الشات | K6: حسب docs/11-CHECKPOINT: ChBack وChSheet اتعملوا 2026-10-11 (ماتحدّثش لونه في الملف)
A7: 6 | B7: الجزء الثالث — DORR AI (367 بند) | C7: ضوابط حاكمة إلزامية لـ DORR AI — HIGH STAKES | D7: 367 | E7: اشتراك الفرق/الشركات (مستقبلي): يُترك كبند مفتوح لمستوى «فريق» بسعر لكل مقعد (Per-seat)، للشركات التي تستخدم DORR AI عبر عدة موظفين — يُحدد لاحقًا عند الحاجة الفعلية، ولا يُبرمج الآن كأولوية. | G7: أزرق — لسه | H7: ⏸ مؤجل بقرار | I7: 2026-10-14 | J7: دُرر AI | K7: الـ spec نفسه بيقول «لا يُبرمج الآن كأولوية»
A8: 7 | B8: الجزء الثالث — DORR AI (367 بند) | C8: 2. قاعدة الدقة والمصداقية | D8: 5 | E8: لا يدّعي DORR AI دقة 100%. | G8: أزرق — لسه | H8: ✅ خلص | I8: 2026-10-14 | J8: دُرر AI | K8: AiEvidencePlanner بيحط القاعدة دي في تعليمات الموديل قبل الإجابة، والـ AiCitationValidator بيراجع اللي يتراجع بعدها (الآيات، والحسابات، والتواريخ، والدولة، والمصادر)
A9: 8 | B9: الجزء الثالث — DORR AI (367 بند) | C9: 2. قاعدة الدقة والمصداقية | D9: 9 | E9: إذا تعارضت مصادر موثوقة، يوضح الخلاف بدل اختيار رأي واحد على أنه يقين. | G9: أزرق — لسه | H9: ✅ خلص | I9: 2026-10-14 | J9: دُرر AI | K9: AiEvidencePlanner بيحط القاعدة دي في تعليمات الموديل قبل الإجابة، والـ AiCitationValidator بيراجع اللي يتراجع بعدها (الآيات، والحسابات، والتواريخ، والدولة، والمصادر)
A10: 9 | B10: الجزء الثالث — DORR AI (367 بند) | C10: 3. Source & Evidence Router | D10: 16 | E10: القانون: النصوص والجهات الرسمية حسب الدولة والاختصاص والتاريخ. | G10: أزرق — لسه | H10: ✅ خلص | I10: 2026-10-14 | J10: دُرر AI | K10: AiEvidencePlanner بيحط القاعدة دي في تعليمات الموديل قبل الإجابة، والـ AiCitationValidator بيراجع اللي يتراجع بعدها (الآيات، والحسابات، والتواريخ، والدولة، والمصادر)
A11: 10 | B11: الجزء الثالث — DORR AI (367 بند) | C11: 3. Source & Evidence Router | D11: 17 | E11: المالية والأعمال: بيانات المستخدم + مصادر رسمية/موثوقة + حسابات قابلة لإعادة التحقق. | G11: أزرق — لسه | H11: ✅ خلص | I11: 2026-10-14 | J11: دُرر AI | K11: AiEvidencePlanner بيحط القاعدة دي في تعليمات الموديل قبل الإجابة، والـ AiCitationValidator بيراجع اللي يتراجع بعدها (الآيات، والحسابات، والتواريخ، والدولة، والمصادر)
A12: 11 | B12: الجزء الثالث — DORR AI (367 بند) | C12: 3. Source & Evidence Router | D12: 18 | E12: الدين: القرآن بنص موثوق، والحديث من مصادر موثوقة، وعدم اختلاق نسبة إلى عالم. | G12: أزرق — لسه | H12: ✅ خلص | I12: 2026-10-14 | J12: دُرر AI | K12: AiEvidencePlanner بيحط القاعدة دي في تعليمات الموديل قبل الإجابة، والـ AiCitationValidator بيراجع اللي يتراجع بعدها (الآيات، والحسابات، والتواريخ، والدولة، والمصادر)
A13: 12 | B13: الجزء الثالث — DORR AI (367 بند) | C13: 3. Source & Evidence Router | D13: 19 | E13: تفسير الأحلام: اجتهادي غير يقيني، مع نسبة الأقوال لمصادر/مفسرين موثوقين فقط عند التحقق منها. | G13: أزرق — لسه | H13: ✅ خلص | I13: 2026-10-14 | J13: دُرر AI | K13: AiEvidencePlanner بيحط القاعدة دي في تعليمات الموديل قبل الإجابة، والـ AiCitationValidator بيراجع اللي يتراجع بعدها (الآيات، والحسابات، والتواريخ، والدولة، والمصادر)
A14: 13 | B14: الجزء الثالث — DORR AI (367 بند) | C14: 4.5 القانون — HIGH STAKES | D14: 79 | E14: يحدد الدولة والاختصاص والتاريخ قبل الجزم. | G14: أزرق — لسه | H14: ✅ خلص | I14: 2026-10-14 | J14: دُرر AI | K14: AiEvidencePlanner بيحط القاعدة دي في تعليمات الموديل قبل الإجابة، والـ AiCitationValidator بيراجع اللي يتراجع بعدها (الآيات، والحسابات، والتواريخ، والدولة، والمصادر)
A15: 14 | B15: الجزء الثالث — DORR AI (367 بند) | C15: 4.5 القانون — HIGH STAKES | D15: 80 | E15: يستخدم النصوص الرسمية الحديثة قدر الإمكان. | G15: أزرق — لسه | H15: ✅ خلص | I15: 2026-10-14 | J15: دُرر AI | K15: AiEvidencePlanner بيحط القاعدة دي في تعليمات الموديل قبل الإجابة، والـ AiCitationValidator بيراجع اللي يتراجع بعدها (الآيات، والحسابات، والتواريخ، والدولة، والمصادر)
A16: 15 | B16: الجزء الثالث — DORR AI (367 بند) | C16: 4.5 القانون — HIGH STAKES | D16: 81 | E16: يميز بين النص القانوني والتفسير والاجتهاد. | G16: أزرق — لسه | H16: ✅ خلص | I16: 2026-10-14 | J16: دُرر AI | K16: AiEvidencePlanner بيحط القاعدة دي في تعليمات الموديل قبل الإجابة، والـ AiCitationValidator بيراجع اللي يتراجع بعدها (الآيات، والحسابات، والتواريخ، والدولة، والمصادر)
A17: 16 | B17: الجزء الثالث — DORR AI (367 بند) | C17: 85. القرآن الكريم | D17: 86 | E17: لا يولد تفسيرًا شخصيًا للآيات. | G17: أزرق — لسه | H17: ✅ خلص | I17: 2026-10-14 | J17: دُرر AI | K17: AiEvidencePlanner بيحط القاعدة دي في تعليمات الموديل قبل الإجابة، والـ AiCitationValidator بيراجع اللي يتراجع بعدها (الآيات، والحسابات، والتواريخ، والدولة، والمصادر)
A18: 17 | B18: الجزء الثالث — DORR AI (367 بند) | C18: 85. القرآن الكريم | D18: 88 | E18: يتحقق من نص الآية واسم السورة ورقم الآية قبل العرض. | G18: أزرق — لسه | H18: ✅ خلص | I18: 2026-10-14 | J18: دُرر AI | K18: AiEvidencePlanner بيحط القاعدة دي في تعليمات الموديل قبل الإجابة، والـ AiCitationValidator بيراجع اللي يتراجع بعدها (الآيات، والحسابات، والتواريخ، والدولة، والمصادر)
... A70: 69 | B70: الجزء الثالث — DORR AI (367 بند) | C70: متطلبات الاعتماد النهائي المشتركة | D70: 7 | E70: Feature Flag مستقل لتفعيل/إيقاف خدمة AI حسب الدولة/المدينة/الفئة. | G70: أزرق — لسه | H70: 🟡 جزئي | I70: 2026-10-14 | J70: دُرر AI | K70: الدولة: اتعمل لشات دُرر AI كله (AiFeatureFlag من نوع service). أدوات الشات بالدولة والمدينة. المدينة لشات دُرر AI والفئة: مفيش مصدر ليهم، والفئة متأجلة بقرار
